Metadata-Version: 2.1
Name: keras-synthetic-genome-sequence
Version: 1.0.2
Summary: Python package to lazily generate synthetic genomic sequences for training od Keras models.
Home-page: https://github.com/LucaCappelletti94/keras_synthetic_genome_sequence
Author: Luca Cappelletti
Author-email: cappelletti.luca94@gmail.com
License: MIT
Platform: UNKNOWN
Classifier: Development Status :: 3 - Alpha
Classifier: License :: OSI Approved :: MIT License
Classifier: Programming Language :: Python :: 3
Provides-Extra: test
